{
  "requestsFinished": 0,
  "requestsFailed": 0,
  "requestsRetries": 0,
  "requestsFailedPerMinute": 0,
  "requestsFinishedPerMinute": 0,
  "requestMinDurationMillis": null,
  "requestMaxDurationMillis": 0,
  "requestTotalFailedDurationMillis": 0,
  "requestTotalFinishedDurationMillis": 0,
  "crawlerStartedAt": "2026-04-13T05:38:12.601Z",
  "crawlerFinishedAt": "2026-04-13T05:38:13.511Z",
  "statsPersistedAt": "2026-04-13T05:38:13.511Z",
  "crawlerRuntimeMillis": 1027,
  "crawlerLastStartTimestamp": 1776058692484,
  "requestRetryHistogram": [],
  "statsId": 10911,
  "requestAvgFailedDurationMillis": null,
  "requestAvgFinishedDurationMillis": null,
  "requestTotalDurationMillis": 0,
  "requestsTotal": 0,
  "requestsWithStatusCode": {},
  "errors": {},
  "retryErrors": {}
}