{
  "requestsFinished": 0,
  "requestsFailed": 0,
  "requestsRetries": 0,
  "requestsFailedPerMinute": 0,
  "requestsFinishedPerMinute": 0,
  "requestMinDurationMillis": null,
  "requestMaxDurationMillis": 0,
  "requestTotalFailedDurationMillis": 0,
  "requestTotalFinishedDurationMillis": 0,
  "crawlerStartedAt": "2026-04-13T05:40:15.251Z",
  "crawlerFinishedAt": "2026-04-13T05:40:16.078Z",
  "statsPersistedAt": "2026-04-13T05:40:16.078Z",
  "crawlerRuntimeMillis": 923,
  "crawlerLastStartTimestamp": 1776058815155,
  "requestRetryHistogram": [],
  "statsId": 11046,
  "requestAvgFailedDurationMillis": null,
  "requestAvgFinishedDurationMillis": null,
  "requestTotalDurationMillis": 0,
  "requestsTotal": 0,
  "requestsWithStatusCode": {},
  "errors": {},
  "retryErrors": {}
}