{
  "requestsFinished": 0,
  "requestsFailed": 0,
  "requestsRetries": 0,
  "requestsFailedPerMinute": 0,
  "requestsFinishedPerMinute": 0,
  "requestMinDurationMillis": null,
  "requestMaxDurationMillis": 0,
  "requestTotalFailedDurationMillis": 0,
  "requestTotalFinishedDurationMillis": 0,
  "crawlerStartedAt": "2026-04-11T13:57:27.638Z",
  "crawlerFinishedAt": "2026-04-11T13:57:28.337Z",
  "statsPersistedAt": "2026-04-11T13:57:28.337Z",
  "crawlerRuntimeMillis": 785,
  "crawlerLastStartTimestamp": 1775915847552,
  "requestRetryHistogram": [],
  "statsId": 183,
  "requestAvgFailedDurationMillis": null,
  "requestAvgFinishedDurationMillis": null,
  "requestTotalDurationMillis": 0,
  "requestsTotal": 0,
  "requestsWithStatusCode": {},
  "errors": {},
  "retryErrors": {}
}