{
  "requestsFinished": 0,
  "requestsFailed": 0,
  "requestsRetries": 0,
  "requestsFailedPerMinute": 0,
  "requestsFinishedPerMinute": 0,
  "requestMinDurationMillis": null,
  "requestMaxDurationMillis": 0,
  "requestTotalFailedDurationMillis": 0,
  "requestTotalFinishedDurationMillis": 0,
  "crawlerStartedAt": "2026-04-12T19:59:07.544Z",
  "crawlerFinishedAt": "2026-04-12T19:59:08.488Z",
  "statsPersistedAt": "2026-04-12T19:59:08.488Z",
  "crawlerRuntimeMillis": 1054,
  "crawlerLastStartTimestamp": 1776023947434,
  "requestRetryHistogram": [],
  "statsId": 7829,
  "requestAvgFailedDurationMillis": null,
  "requestAvgFinishedDurationMillis": null,
  "requestTotalDurationMillis": 0,
  "requestsTotal": 0,
  "requestsWithStatusCode": {},
  "errors": {},
  "retryErrors": {}
}