{
  "requestsFinished": 0,
  "requestsFailed": 0,
  "requestsRetries": 0,
  "requestsFailedPerMinute": 0,
  "requestsFinishedPerMinute": 0,
  "requestMinDurationMillis": null,
  "requestMaxDurationMillis": 0,
  "requestTotalFailedDurationMillis": 0,
  "requestTotalFinishedDurationMillis": 0,
  "crawlerStartedAt": "2026-04-12T19:14:36.103Z",
  "crawlerFinishedAt": "2026-04-12T19:14:36.812Z",
  "statsPersistedAt": "2026-04-12T19:14:36.812Z",
  "crawlerRuntimeMillis": 798,
  "crawlerLastStartTimestamp": 1776021276014,
  "requestRetryHistogram": [],
  "statsId": 4240,
  "requestAvgFailedDurationMillis": null,
  "requestAvgFinishedDurationMillis": null,
  "requestTotalDurationMillis": 0,
  "requestsTotal": 0,
  "requestsWithStatusCode": {},
  "errors": {},
  "retryErrors": {}
}