{
  "requestsFinished": 0,
  "requestsFailed": 0,
  "requestsRetries": 0,
  "requestsFailedPerMinute": 0,
  "requestsFinishedPerMinute": 0,
  "requestMinDurationMillis": null,
  "requestMaxDurationMillis": 0,
  "requestTotalFailedDurationMillis": 0,
  "requestTotalFinishedDurationMillis": 0,
  "crawlerStartedAt": "2026-04-12T19:59:26.384Z",
  "crawlerFinishedAt": "2026-04-12T19:59:27.281Z",
  "statsPersistedAt": "2026-04-12T19:59:27.281Z",
  "crawlerRuntimeMillis": 1188,
  "crawlerLastStartTimestamp": 1776023966093,
  "requestRetryHistogram": [],
  "statsId": 7847,
  "requestAvgFailedDurationMillis": null,
  "requestAvgFinishedDurationMillis": null,
  "requestTotalDurationMillis": 0,
  "requestsTotal": 0,
  "requestsWithStatusCode": {},
  "errors": {},
  "retryErrors": {}
}