{
  "requestsFinished": 0,
  "requestsFailed": 0,
  "requestsRetries": 0,
  "requestsFailedPerMinute": 0,
  "requestsFinishedPerMinute": 0,
  "requestMinDurationMillis": null,
  "requestMaxDurationMillis": 0,
  "requestTotalFailedDurationMillis": 0,
  "requestTotalFinishedDurationMillis": 0,
  "crawlerStartedAt": "2026-04-12T19:33:07.069Z",
  "crawlerFinishedAt": "2026-04-12T19:33:07.629Z",
  "statsPersistedAt": "2026-04-12T19:33:07.629Z",
  "crawlerRuntimeMillis": 674,
  "crawlerLastStartTimestamp": 1776022386955,
  "requestRetryHistogram": [],
  "statsId": 5803,
  "requestAvgFailedDurationMillis": null,
  "requestAvgFinishedDurationMillis": null,
  "requestTotalDurationMillis": 0,
  "requestsTotal": 0,
  "requestsWithStatusCode": {},
  "errors": {},
  "retryErrors": {}
}