{
  "requestsFinished": 0,
  "requestsFailed": 0,
  "requestsRetries": 0,
  "requestsFailedPerMinute": 0,
  "requestsFinishedPerMinute": 0,
  "requestMinDurationMillis": null,
  "requestMaxDurationMillis": 0,
  "requestTotalFailedDurationMillis": 0,
  "requestTotalFinishedDurationMillis": 0,
  "crawlerStartedAt": "2026-04-12T19:42:02.957Z",
  "crawlerFinishedAt": "2026-04-12T19:42:03.656Z",
  "statsPersistedAt": "2026-04-12T19:42:03.656Z",
  "crawlerRuntimeMillis": 821,
  "crawlerLastStartTimestamp": 1776022922835,
  "requestRetryHistogram": [],
  "statsId": 6547,
  "requestAvgFailedDurationMillis": null,
  "requestAvgFinishedDurationMillis": null,
  "requestTotalDurationMillis": 0,
  "requestsTotal": 0,
  "requestsWithStatusCode": {},
  "errors": {},
  "retryErrors": {}
}